isfreemail/__init__.py
isfreemail/check.py
isfreemail/freeservers.py
isfreemail/tests/__init__.py
isfreemail/tests/test_isfreemail.py
isfreemail-0.1.5.dist-info/LICENSE
isfreemail-0.1.5.dist-info/METADATA
isfreemail-0.1.5.dist-info/WHEEL
isfreemail-0.1.5.dist-info/top_level.txt
isfreemail-0.1.5.dist-info/RECORD
